pdfwork/__init__.py
pdfwork/actions.py
pdfwork/cli.py
pdfwork/exceptions.py
pdfwork/outline.py
pdfwork/range.py
pdfwork/utils.py
pdfwork-0.4.0.dist-info/entry_points.txt
pdfwork-0.4.0.dist-info/WHEEL
pdfwork-0.4.0.dist-info/METADATA
pdfwork-0.4.0.dist-info/RECORD
