Metadata-Version: 2.1
Name: pdfwork
Version: 0.4.0
Summary: 基于 pikepdf 封装的命令行工具，处理 PDF 文件用
Home-page: https://github.com/zombie110year/pdfwork
License: MIT
Author: zombie110year
Author-email: zombie110year@outlook.com
Requires-Python: >=3.8,<4.0
Classifier: Environment :: Console
Classifier: License :: OSI Approved :: MIT License
Classifier: Programming Language :: Python :: 3
Classifier: Programming Language :: Python :: 3.8
Classifier: Programming Language :: Python :: 3.9
Requires-Dist: more-itertools (>=8.3.0,<9.0.0)
Requires-Dist: pikepdf (>=2.0.0,<3.0.0)
Requires-Dist: tqdm (>=4.52.0,<5.0.0)
Requires-Dist: typer (>=0.3.2,<0.4.0)
Project-URL: Bug Tracker, https://github.com/zombie110year/pdfwork/issues
Project-URL: Repository, https://github.com/zombie110year/pdfwork.git
